Workbook

Sheet Sep'25
A1: Estado de Resultados 2025
A2: Concepto | B2: 45901 | C2: %
A3: Ventas Netas | B3: ='Ventas Oct 2025'!J47 -> 112012903 | C3: 1
A4: Descuentos Realizados | B4: ='Ventas Oct 2025'!K47 -> 4033636.4 | C4: =(B4*C3)/B3 -> 0.036010462
A5: Total Ingresos | B5: =B3-B4 -> 1.0797927e+08 | C5: 1
A6: Costo total | B6: ='Ventas Oct 2025'!I47 -> 19895234 | C6: 0.33
A7: Utilidad Marginal | B7: =B5-B6 -> 88084032 | C7: =(B7*C5)/B5 -> 0.81574949
A10: GASTOS VARIABLES | B10: =SUM(B11:B18) -> 2587186.7 | C10: =(B10*$C$5)/$B$5 -> 0.023960032
A11: COMISIONES BANCARIAS | B11: =+Gastos!C7 -> 0 | C11: =(B11*$C$5)/$B$5 -> 0
A12: COMISIONES DISTRIBUIDORES | B12: =+Gastos!C12 -> 0 | C12: =(B12*$C$5)/$B$5 -> 0
A13: COMISIONES VENTAS | B13: =+Gastos!C10 -> 0 | C13: =(B13*$C$5)/$B$5 -> 0
A14: EXTRAORDINARIOS | B14: =+Gastos!C31 -> 2587186.7 | C14: =(B14*$C$5)/$B$5 -> 0.023960032
A15: FLETES | B15: =+Gastos!C33 -> 0 | C15: =(B15*$C$5)/$B$5 -> 0
A16: IMPUESTOS | B16: =+Gastos!C166 -> 0 | C16: =(B16*$C$5)/$B$5 -> 0
A17: MARKETING | B17: 0 | C17: =(B17*$C$5)/$B$5 -> 0
A18: PUESTA EN MARCHA | B18: 0 | C18: =(B18*$C$5)/$B$5 -> 0
A20: GASTOS FIJOS | B20: =SUM(B21:B22) -> 4052388.2 | C20: =(B20*$C$5)/$B$5 -> 0.037529318
A21: LOCAL | B21: =+Gastos!C184 -> 439900.25 | C21: =(B21*$C$5)/$B$5 -> 0.0040739326
A22: SUELDOS | B22: =+Gastos!C193 -> 3612488 | C22: =(B22*$C$5)/$B$5 -> 0.033455386
A24: GASTOS TOTALES | B24: =+B10+B20 -> 6639574.9
A26: UTILIDAD NETA | B26: =B7-B10-B20 -> 81444457 | C26: =(B26*C5)/B5 -> 0.75426014
A29: INVERSIONES
A30: INVERSIONES

Sheet Gastos
A1: Fecha | B1: Descripción | C1: Importe | D1: Categoría | E1: SubCategoría
B2: Debito Com. Varias | Transf. al Ext. | D2: Impuestos | E2: Comisiones Bancarias
B3: Debito Com. Varias | Transf. al Ext. | D3: Impuestos | E3: Comisiones Bancarias
B4: Comisiones Bancarias | D4: Comisiones Bancarias | E4: Comisiones Bancarias
B5: Comisiones Bancarias | D5: Comisiones Bancarias | E5: Comisiones Bancarias
B6: Comisiones Bancarias | D6: Comisiones Bancarias | E6: Comisiones Bancarias
B7: Comisiones Bancarias | C7: =SUM(C2:C6) -> 0
B8: Comisiones Cynthia | Sep´25 | D8: Comisiones Ventas | E8: Comisiones Ventas
B9: Comisiones Lelia | Sep´25 | D9: Comisiones Ventas | E9: Comisiones Ventas
B10: Comisiones de Ventas | C10: =SUM(C8:C9) -> 0
B11: Comisiones Javier Sep´25 | D11: Comisiones Ventas | E11: Comisiones Ventas
B12: Comisiones Distribuidores | C12: =SUM(C11) -> 0
A13: 45904 | B13: Pago | Full Electric SRL | Fact 0003-00002818 | C13: 127396.67 | D13: Mantenimiento | E13: Material Electrico | F13: Clavija y contacto 3P 32 Amp
A14: 45905 | B14: Pago | Alba Posse Patricia Maria | Fact 00001-00000015 | C14: 88000 | D14: Otros Servicios | E14: Selección de Personal | F14: Servicio de Selección de Personal
A15: 45905 | B15: Pago | Autoelevadores y Gruas | Sep 2025 | Fact 7476 | C15: 257293.4 | D15: Otros Servicios | E15: Alquiler | F15: Almacenaje de hornos
A16: 45905 | B16: Pago | Petreca Gonzalo Marcelo | Fact 0088 | C16: 1008250 | D16: Marketing | E16: Publicidad | F16: Creacion de contenido
A17: 45905 | B17: Pago | Antonio Francisco Celio | Fact 36121 | C17: 1106246.6 | D17: Mantenimiento | E17: Ferreteria | F17: Manometros
B18: Pago | Polypel Embalajes | Fact 00002-00029647 | D18: Mantenimiento | E18: Ferreteria
B19: Pago | Suppa Rodrigo Pablo | Fact 00002-00000482 | D19: Marketing | E19: Publicidad
B20: Pago | Suppa Rodrigo Pablo | Fact 00002-00000483 | D20: Marketing | E20: Publicidad
B21: Pago | BLG Net SRL | Fact 00005-00000612 | D21: Mantenimiento | E21: Material Electrico
B22: Pago | Antonio Francisco Celio | Fact 00005-00036434 | D22: Activos | E22: Accesorios
B23: Pago | Suppa Rodrigo Pablo | Fact 00002-00000484 | D23: Marketing | E23: Publicidad
B24: Pago | Desarrollo de Soluciones Digitales | Fact 00002-00000008 | D24: Otros Servicios | E24: App Sumar
B25: Pago | Mobilarg del Lobo Alejandro | Fact 00012-00001279 | D25: Mobiliario | E25: Mobiliario
B26: Pago | Sanitarios Kerrey | Fact 00004-00000973 | D26: Mantenimiento | E26: Ferreteria
B27: Pago | Indumentaria RGS | Fact 00002-00001680 | D27: Mantenimiento | E27: Ferreteria
B28: Pago | Apyce | Fact 00003-00003946 | D28: Otros Servicios | E28: Gastos Administrativos
B29: Pago |Lagatta Carlos Adrian | Fact 00006-00004239 | D29: Otros Servicios | E29: Gastos Administrativos
B30: Pago | Apyce | Fact 00003-00003946 | D30: Otros Servicios | E30: Gastos Administrativos
B31: Extraordinarios | C31: =SUM(C13:C30) -> 2587186.7
B32: Pago | Autoelevadores y Gruas | Oct 2025 | Fact 7537 | D32: Fletes | E32: Fletes
B33: Fletes | C33: =C32 -> 0
A34: 45901 | B34: Imp. Ing. Brutos Sircreb | C34: 9983.31 | D34: Impuestos | E34: Sircreb
A35: 45901 | B35: Impuesto Deb. Ley 25.413 | C35: 22233.36 | D35: Impuestos | E35: Ley 25.413
A36: 45901 | B36: Impuesto Cre. Ley 25.413 | C36: 11979.97 | D36: Impuestos | E36: Ley 25.413
A37: 45901 | B37: Impuesto Deb. Ley 25.413 | C37: 59.9 | D37: Impuestos | E37: Ley 25.413
A38: 45903 | B38: Imp. Ing. Brutos Sircreb | C38: 4000 | D38: Impuestos | E38: Sircreb
A39: 45903 | B39: Imp. Ing. Brutos Sircreb | C39: 2000 | D39: Impuestos | E39: Sircreb
A40: 45903 | B40: Imp. Ing. Brutos Sircreb | C40: 5890 | D40: Impuestos | E40: Sircreb
A41: 45903 | B41: Impuesto Deb. Ley 25.413 | C41: 252.22 | D41: Impuestos | E41: Ley 25.413
A42: 45903 | B42: Impuesto Cre. Ley 25.413 | C42: 14268 | D42: Impuestos | E42: Ley 25.413
A43: 45903 | B43: Impuesto Deb. Ley 25.413 | C43: 71.34 | D43: Impuestos | E43: Ley 25.413
A44: 45903 | B44: Imp. Ing. Brutos Sircreb | C44: 2500 | D44: Impuestos | E44: Sircreb
A45: 45903 | B45: Imp. Ing. Brutos Sircreb | C45: 7500 | D45: Impuestos | E45: Sircreb
... A53: 45905 | B53: Imp. Ing. Brutos Sircreb | C53: 15206.37 | D53: Impuestos | E53: Sircreb
B54: Percep IVA | D54: Impuestos | E54: Iva
B55: Imp. Ing. Brutos Capital Federal | D55: Impuestos | E55: Ingresos Brutos
B56: Impuesto Ley 25.413 | D56: Impuestos | E56: Ley 25.413
B57: Imp. Ing. Brutos Sircreb | D57: Impuestos | E57: Sircreb
B58: Imp. Ing. Brutos Sircreb | D58: Impuestos | E58: Sircreb
B59: Imp. Ing. Brutos Sircreb | D59: Impuestos | E59: Sircreb
B60: Imp. Ing. Brutos Sircreb | D60: Impuestos | E60: Sircreb
B61: Impuesto Deb. Ley 25.413 | D61: Impuestos | E61: Ley 25.413
B62: Impuesto Cre. Ley 25.413 | D62: Impuestos | E62: Ley 25.413
B63: Impuesto Deb. Ley 25.413 | D63: Impuestos | E63: Ley 25.413
B64: Pago | Cargas Sociales | La Estrella | Sep'25 | D64: Impuestos | E64: La Estrella
B65: Pago | Cargas Sociales | SEC | Sep'25 | D65: Impuestos | E65: SEC
... B165: Impuesto Deb. Ley 25.413 | D165: Impuestos | E165: Ley 25.413
B166: =+D165 -> Impuestos | C166: =SUM(C54:C165) -> 0
A167: 45901 | B167: Pago | Prosegur Septiembre 2025 Deb Autom. | C167: 93071.25 | D167: Local | E167: Seguridad
A168: 45903 | B168: Pago | Cablevision | Deb Autom. Sep 2025 | C168: 42037 | D168: Local | E168: ABL
A169: 45905 | B169: Pago | Viviana Fuertes | Alquiler | Fact 00002-00000258 | C169: 304792 | D169: Local | E169: Alquiler
B170: Pago | Nicolas Manuel Torres | Fact Mercado Libre | D170: Local | E170: Plataforma Merdado Libre
B171: Pago | Luciano Alejandro | Fact Mercado Libre | D171: Local | E171: Plataforma Merdado Libre
B172: Pago | Luciano Alejandro | Fact Mercado Libre | D172: Local | E172: Plataforma Merdado Libre
B173: Pago | GCBA INM/ABL | D173: Local | E173: Alquiler
B174: Pago | GCBA INM/ABL | D174: Local | E174: Alquiler
B175: Pago | Pay Per Tic | Deb Autom | D175: Local | E175: Internet
B176: Pago | Personal Flow | Deb Autom | D176: Local | E176: Internet
B177: Pago | Soluciones Online | Oct 2025 | Deb. Autom. | Fact 473666 | D177: Local | E177: Internet
B178: Pago | Autoelevadores y Gruas | Oct 2025 | Fact 7537 | D178: Local | E178: Alquiler
B179: Pago | Veronica Valeria Rigante | Fact 00002-00000238 | D179: Local | E179: Honorarios Contables
B180: Pago | Viviana Fuertes | Alquiler | Fact 00002-00000264 | D180: Local | E180: Alquiler
B181: Pago | Leonardo Agustin | Fact Mercado Libre | D181: Local | E181: Plataforma Merdado Libre
... B183: Alquiler | Oct'25 | D183: Local | E183: Alquiler
B184: Local | C184: =SUM(C167:C183) -> 439900.25
A185: 45901 | B185: Pago | Sueldo Lelia Bertoni | Ago'25 | C185: 567205 | D185: Sueldos | E185: Sueldos
A186: 45901 | B186: Pago | Sueldo Cynthia Fernández | Ago'25 | C186: 572878 | D186: Sueldos | E186: Sueldos
A187: 45901 | B187: Pago | Sueldo Diego Argiró | Ago'25 | C187: 2472405 | D187: Sueldos | E187: Sueldos
B188: Pago | Adelanta Vacaciones Lelia Bertoni | Ago'25 | D188: Sueldos | E188: Sueldos
B189: Sueldo Cynthia | Ago´25 | D189: Sueldos | E189: Sueldos
B190: Sueldo Lelia| Ago´25 | D190: Sueldos | E190: Sueldos
B191: Sueldo Diego| Ago´25 | D191: Sueldos | E191: Sueldos
B192: Sueldo Stefania Ago´25 | D192: Sueldos | E192: Sueldos
B193: Sueldos | C193: =SUM(C185:C192) -> 3612488

Sheet Ventas Sep´25

Sheet Ventas Oct 2025
A1: Tipo de Operacion | B1: ID Operacion | C1: Status | D1: Cliente | E1: Vendedor | F1: Referido | G1: Correo | H1: Equipo | I1: Costo | J1: Unitario | K1: Descuento | L1: Precio con descuento | M1: Subtotal | N1: IVA 10-5% | O1: IVA 21% | P1: Total Cotización | Q1: % Factura | R1: Total Factura | S1: Monto Factura | T1: Monto Efectivo
A2: Venta | B2: 273 | C2: Pago Realizado | D2: Jairo Ayrton Carrizo Peñaloza | E2: Lelia | F2: APYCE | G2: jairoayrtoncarrizopenaloza@gmail.com | H2: Base para horno | I2: 210000 | J2: 250000 | L2: =ExportFacturacion[[#This Row],[Unitario]]-ExportFacturacion[[#This Row],[Descuento]] -> 250000 | M2: 250.000,00 | N2: 0,00 | O2: 52.500,00 | P2: 302.500,00 | Q2: 100 | R2: 302.500,00 | S2: 250.000,00 | T2: 0,00
A3: Venta | B3: 299 | C3: Despachado | D3: Lucas Moreno | E3: Cynthia | H3: Pro Gas 6-1 | I3: 598486.37 | J3: 3516000 | L3: =ExportFacturacion[[#This Row],[Unitario]]-ExportFacturacion[[#This Row],[Descuento]] -> 3516000 | M3: 3.516.000,00 | N3: 369.180,00 | O3: 0,00 | P3: 3.885.180,00 | Q3: 50 | R3: 1.942.590,00 | S3: 1.758.000,00 | T3: 1.758.000,00
A4: Venta | B4: 307 | C4: Pago Realizado | D4: Julian Palamara | E4: Cynthia | G4: Juliipalamara@gmail.com | H4: Pro Gas 12-2 | I4: 1114422.9 | J4: 5860000 | L4: =ExportFacturacion[[#This Row],[Unitario]]-ExportFacturacion[[#This Row],[Descuento]] -> 5860000 | M4: 5.860.000,00 | N4: 615.300,00 | O4: 0,00 | P4: 6.475.300,00 | Q4: 50 | R4: 3.237.650,00 | S4: 2.930.000,00 | T4: 2.930.000,00
A5: Venta | B5: 324 | C5: Pago Realizado | D5: Lorenzo Sanchez | E5: Lelia | G5: lorenzosz.41@gmail.com | H5: Pro Gas 12-2 | I5: 1114422.9 | J5: 6446000 | K5: =ExportFacturacion[[#This Row],[Unitario]]*5% -> 322300 | L5: =ExportFacturacion[[#This Row],[Unitario]]-ExportFacturacion[[#This Row],[Descuento]] -> 6123700 | M5: 6.237.795,00 | N5: 654.968,48 | O5: 0,00 | P5: 6.892.763,48 | Q5: 100 | R5: 6.892.763,48 | S5: 6.237.795,00 | T5: 0,00
H6: Cepillo p/piedra | I6: 29803.21 | J6: 120100 | K6: =ExportFacturacion[[#This Row],[Unitario]]*5% -> 6005 | L6: =ExportFacturacion[[#This Row],[Unitario]]-ExportFacturacion[[#This Row],[Descuento]] -> 114095
A7: Venta | B7: 354 | C7: Pago Realizado | D7: Mario Cesar Scattolini | E7: Lelia | G7: mario.scattolini@hotmail.com | H7: Pro Gas 12-2 | I7: 1114422.9 | J7: 6446000 | L7: =ExportFacturacion[[#This Row],[Unitario]]-ExportFacturacion[[#This Row],[Descuento]] -> 6446000 | M7: 6.446.000,00 | N7: 676.830,00 | O7: 0,00 | P7: 7.122.830,00 | Q7: 100 | R7: 7.122.830,00 | S7: 6.446.000,00 | T7: 0,00
A8: Venta | B8: 368 | C8: Pago Realizado | D8: Diego Alejandro Bacigalupi | E8: Lelia | F8: APYCE | G8: diegocarthu@gmail.com | H8: FN1 Pro | I8: 220132.92 | J8: 1188000 | L8: =ExportFacturacion[[#This Row],[Unitario]]-ExportFacturacion[[#This Row],[Descuento]] -> 1188000 | M8: 1.188.000,00 | N8: 124.740,00 | O8: 0,00 | P8: 1.312.740,00 | Q8: 100 | R8: 1.312.740,00 | S8: 1.188.000,00 | T8: 0,00
A9: Venta | B9: 369 | C9: Pago Realizado | D9: Victor Ochoa | E9: Lelia | H9: Pro Gas 6-1 | I9: 598486.37 | J9: 3867600 | L9: =ExportFacturacion[[#This Row],[Unitario]]-ExportFacturacion[[#This Row],[Descuento]] -> 3867600 | M9: 3.867.600,00 | N9: 406.098,00 | O9: 0,00 | P9: 4.273.698,00 | Q9: 100 | R9: 4.273.698,00 | S9: 3.867.600,00 | T9: 0,00
A10: Venta | B10: 372 | C10: Despachado | D10: Patricio Hernan Rienzi | E10: Cynthia | H10: Base para horno | I10: 210000 | J10: 250000 | L10: =ExportFacturacion[[#This Row],[Unitario]]-ExportFacturacion[[#This Row],[Descuento]] -> 250000 | M10: 4.117.600,00 | N10: 406.098,00 | O10: 52.500,00 | P10: 4.576.198,00 | Q10: 100 | R10: 4.576.198,00 | S10: 4.117.600,00 | T10: 0,00
H11: Pro Gas 6-1 | I11: 598486.37 | J11: 3867600 | L11: =ExportFacturacion[[#This Row],[Unitario]]-ExportFacturacion[[#This Row],[Descuento]] -> 3867600
A12: Venta | B12: 377 | C12: Despachado | D12: Federico Cortez | E12: Cynthia | G12: federsfc@gmail.com | H12: FN1 Pro | I12: 220132.92 | J12: 1188000 | L12: =ExportFacturacion[[#This Row],[Unitario]]-ExportFacturacion[[#This Row],[Descuento]] -> 1188000 | M12: 1.188.000,00 | N12: 124.740,00 | O12: 0,00 | P12: 1.312.740,00 | Q12: 100 | R12: 1.312.740,00 | S12: 1.188.000,00 | T12: 0,00
A13: Venta | B13: 384 | C13: Despachado | D13: Javier Maximiliano Coccaro | E13: Cynthia | F13: Luciano | G13: jc-producciones2005@hotmail.com | H13: Aceitera | I13: 16557.34 | J13: 75100 | L13: =ExportFacturacion[[#This Row],[Unitario]]-ExportFacturacion[[#This Row],[Descuento]] -> 75100 | M13: 75.100,00 | N13: 7.885,50 | O13: 0,00 | P13: 82.985,50 | Q13: 100 | R13: 82.985,50 | S13: 75.100,00 | T13: 0,00
A14: Venta | B14: 388 | C14: Despachado | D14: Michele Conte | E14: Cynthia | H14: FN2 Pro | I14: 398990.91 | J14: 2211000 | L14: =ExportFacturacion[[#This Row],[Unitario]]-ExportFacturacion[[#This Row],[Descuento]] -> 2211000 | M14: 2.211.000,00 | N14: 232.155,00 | O14: 0,00 | P14: 2.443.155,00 | Q14: 100 | R14: 2.443.155,00 | S14: 2.211.000,00 | T14: 0,00
A15: Venta | B15: 389 | C15: Pago Realizado | D15: Mariela Patricia Ambrosio | E15: Lelia | G15: Leperefacundo@gmail.com | H15: Pro Gas 6-1 | I15: 598486.37 | J15: 3867600 | L15: =ExportFacturacion[[#This Row],[Unitario]]-ExportFacturacion[[#This Row],[Descuento]] -> 3867600 | M15: 3.867.600,00 | N15: 406.098,00 | O15: 0,00 | P15: 4.273.698,00 | Q15: 50 | R15: 2.136.849,00 | S15: 1.933.800,00 | T15: 1.933.800,00
A16: Venta | B16: 394 | C16: Pago Realizado | D16: Tomas Alvarez | E16: Lelia | H16: FN2 Pro | I16: 398990.91 | J16: 2211000 | L16: =ExportFacturacion[[#This Row],[Unitario]]-ExportFacturacion[[#This Row],[Descuento]] -> 2211000 | M16: 2.211.000,00 | N16: 232.155,00 | O16: 0,00 | P16: 2.443.155,00 | Q16: 100 | R16: 2.443.155,00 | S16: 2.211.000,00 | T16: 0,00
A17: Venta | B17: 395 | C17: Pago Realizado | D17: Claudio Alejandro Sala | E17: Lelia | H17: Pro Gas 6-1 | I17: 598486.37 | J17: 3867600 | K17: =ExportFacturacion[[#This Row],[Unitario]]*5% -> 193380 | L17: =ExportFacturacion[[#This Row],[Unitario]]-ExportFacturacion[[#This Row],[Descuento]] -> 3674220 | M17: 3.674.220,00 | N17: 385.793,10 | O17: 0,00 | P17: 4.060.013,10 | Q17: 50 | R17: 2.030.006,55 | S17: 1.837.110,00 | T17: 1.837.110,00
A18: Venta | B18: 398 | C18: Pago Realizado | D18: Diego Mandarino | E18: Cynthia | H18: Pro Gas 3-1 | J18: 3179000 | L18: =ExportFacturacion[[#This Row],[Unitario]]-ExportFacturacion[[#This Row],[Descuento]] -> 3179000 | M18: 3.179.000,00 | N18: 333.795,00 | O18: 0,00 | P18: 3.512.795,00 | Q18: 50 | R18: 1.756.397,50 | S18: 1.589.500,00 | T18: 1.589.500,00
A19: Venta | B19: 399 | C19: Pago Realizado | D19: Juan Manuel Torres Caffaro (Combo 6) | E19: Lelia | H19: Mesa Fria 2 Puertas | I19: 1630897.6 | J19: 6400000 | L19: =ExportFacturacion[[#This Row],[Unitario]]-ExportFacturacion[[#This Row],[Descuento]] -> 6400000 | M19: 6.400.000,00 | N19: 672.000,00 | O19: 0,00 | P19: 7.072.000,00 | Q19: 100 | R19: 7.072.000,00 | S19: 6.400.000,00 | T19: 0,00
H20: Pro Gas 6-1 | I20: 598486.37 | L20: =ExportFacturacion[[#This Row],[Unitario]]-ExportFacturacion[[#This Row],[Descuento]] -> 0
H21: Pala | I21: 28147.47 | L21: =ExportFacturacion[[#This Row],[Unitario]]-ExportFacturacion[[#This Row],[Descuento]] -> 0
H22: Pala | I22: 28147.47 | L22: =ExportFacturacion[[#This Row],[Unitario]]-ExportFacturacion[[#This Row],[Descuento]] -> 0
A23: Venta | B23: 402 | C23: Pago Realizado | D23: Tomas Alaniz | E23: Lelia | H23: FN1 Pro | I23: 220132.92 | J23: 1188000 | L23: =ExportFacturacion[[#This Row],[Unitario]]-ExportFacturacion[[#This Row],[Descuento]] -> 1188000 | M23: 1.188.000,00 | N23: 124.740,00 | O23: 0,00 | P23: 1.312.740,00 | Q23: 100 | R23: 1.312.740,00 | S23: 1.188.000,00 | T23: 0,00
A24: Venta | B24: 412 | C24: Pago Realizado | D24: Juan Diego Rondon | E24: Lelia | H24: FN1 Pro | I24: 220132.92 | J24: 1188000 | L24: =ExportFacturacion[[#This Row],[Unitario]]-ExportFacturacion[[#This Row],[Descuento]] -> 1188000 | M24: 1.188.000,00 | N24: 124.740,00 | O24: 0,00 | P24: 1.312.740,00 | Q24: 100 | R24: 1.312.740,00 | S24: 1.188.000,00 | T24: 0,00
A25: Venta | B25: 421 | C25: Despachado | D25: Fosmi Srl | E25: Cynthia | F25: JAVIER | H25: Pro Gas 12-2 | I25: 1114422.9 | J25: 6446000 | K25: =ExportFacturacion[[#This Row],[Unitario]]*13% -> 837980 | L25: =ExportFacturacion[[#This Row],[Unitario]]-ExportFacturacion[[#This Row],[Descuento]] -> 5608020 | M25: 6.641.580,00 | N25: 697.365,90 | O25: 0,00 | P25: 7.338.945,90 | Q25: 50 | R25: 3.669.472,95 | S25: 3.320.790,00 | T25: 3.320.790,00
H26: FN1 Pro | I26: 220132.92 | J26: 1188000 | K26: =ExportFacturacion[[#This Row],[Unitario]]*13% -> 154440 | L26: =ExportFacturacion[[#This Row],[Unitario]]-ExportFacturacion[[#This Row],[Descuento]] -> 1033560
A27: Venta | B27: 422 | C27: Pago Realizado | D27: Antonio Ingaldi | E27: Cynthia | G27: Tony.ingaldi55@gmail.com | H27: FN1 Pro | I27: 220132.92 | J27: 1188000 | L27: =ExportFacturacion[[#This Row],[Unitario]]-ExportFacturacion[[#This Row],[Descuento]] -> 1188000 | M27: 1.188.000,00 | N27: 124.740,00 | O27: 0,00 | P27: 1.312.740,00 | Q27: 50 | R27: 656.370,00 | S27: 594.000,00 | T27: 594.000,00
A28: Venta | B28: 436 | C28: Pago Realizado | D28: Ricardo Alberto Salvatierra | E28: Cynthia | G28: Richy_1431@hotmail.com | H28: Pro Gas 6-1 | I28: 598486.37 | J28: 3867600 | K28: =ExportFacturacion[[#This Row],[Unitario]]*20% -> 773520 | L28: =ExportFacturacion[[#This Row],[Unitario]]-ExportFacturacion[[#This Row],[Descuento]] -> 3094080 | M28: 3.094.080,00 | N28: 324.878,40 | O28: 0,00 | P28: 3.418.958,40 | Q28: 100 | R28: 3.418.958,40 | S28: 3.094.080,00 | T28: 0,00
A29: Venta | B29: 444 | C29: Despachado | D29: Guido Gabriele | E29: Cynthia | G29: guidogabriele.gg@gmail.com | H29: Pro Gas 90 | I29: 1120931.7 | J29: 4350000 | K29: =ExportFacturacion[[#This Row],[Unitario]]*25% -> 1087500 | L29: =ExportFacturacion[[#This Row],[Unitario]]-ExportFacturacion[[#This Row],[Descuento]] -> 3262500 | M29: 3.262.500,00 | N29: 342.562,50 | O29: 0,00 | P29: 3.605.062,50 | Q29: 50 | R29: 1.802.531,25 | S29: 1.631.250,00 | T29: 1.631.250,00
A30: Venta | B30: 446 | C30: Pago Realizado | D30: Romana Miccio | E30: Lelia | G30: romanamiccio@gmail.com | H30: Aceitera | I30: 16557.34 | J30: 75100 | L30: =ExportFacturacion[[#This Row],[Unitario]]-ExportFacturacion[[#This Row],[Descuento]] -> 75100 | M30: 256.100,00 | N30: 26.890,50 | O30: 0,00 | P30: 282.990,50 | Q30: 100 | R30: 282.990,50 | S30: 256.100,00 | T30: 0,00
H31: Pala | I31: 28147.47 | J31: 80000 | L31: =ExportFacturacion[[#This Row],[Unitario]]-ExportFacturacion[[#This Row],[Descuento]] -> 80000
H32: Box Kit x3 | J32: 101000 | L32: =ExportFacturacion[[#This Row],[Unitario]]-ExportFacturacion[[#This Row],[Descuento]] -> 101000
A33: Venta | B33: 448 | C33: Pago Realizado | D33: Oscar Waldemar Flaumer | E33: Lelia | H33: Pro Gas 6-1 | I33: 598486.37 | J33: 3867600 | L33: =ExportFacturacion[[#This Row],[Unitario]]-ExportFacturacion[[#This Row],[Descuento]] -> 3867600 | M33: 3.867.600,00 | N33: 406.098,00 | O33: 0,00 | P33: 4.273.698,00 | Q33: 50 | R33: 2.136.849,00 | S33: 1.933.800,00 | T33: 1.933.800,00
A34: Venta | B34: 449 | C34: Pago Realizado | D34: Alberto Néstor Ferrero | E34: Lelia | G34: adm2centralg@gmail.com | H34: Pro Gas 16-2 | J34: 9180000 | L34: =ExportFacturacion[[#This Row],[Unitario]]-ExportFacturacion[[#This Row],[Descuento]] -> 9180000 | M34: 9.180.000,00 | N34: 963.900,00 | O34: 0,00 | P34: 10.143.900,00 | Q34: 50 | R34: 5.071.950,00 | S34: 4.590.000,00 | T34: 4.590.000,00
A35: Venta | B35: 451 | C35: Despachado | D35: Agustin Perruccio | E35: Cynthia | H35: Pro Gas 6-1 | I35: 598486.37 | J35: 3867600 | L35: =ExportFacturacion[[#This Row],[Unitario]]-ExportFacturacion[[#This Row],[Descuento]] -> 3867600 | M35: 3.867.600,00 | N35: 406.098,00 | O35: 0,00 | P35: 4.273.698,00 | Q35: 100 | R35: 4.273.698,00 | S35: 3.867.600,00 | T35: 0,00
A36: Venta | B36: 462 | C36: Pago Realizado | D36: Ricardo Alberto Salvatierra | E36: Cynthia | G36: Richy_1431@hotmail.com | H36: Regulador | J36: 106000 | L36: =ExportFacturacion[[#This Row],[Unitario]]-ExportFacturacion[[#This Row],[Descuento]] -> 106000 | M36: 106.000,00 | N36: 0,00 | O36: 22.260,00 | P36: 128.260,00 | Q36: 100 | R36: 128.260,00 | S36: 106.000,00 | T36: 0,00
A37: Venta | B37: 465 | C37: Pago Realizado | D37: Oscar Waldemar Flaumer | E37: Lelia | G37: juanberticje9@gmail.com | H37: Mesa Fria 2 Puertas | I37: 1630897.6 | J37: 3949803 | K37: =ExportFacturacion[[#This Row],[Unitario]]*10% -> 394980.3 | L37: =ExportFacturacion[[#This Row],[Unitario]]-ExportFacturacion[[#This Row],[Descuento]] -> 3554822.7 | M37: 3.554.822,70 | N37: 373.256,38 | O37: 0,00 | P37: 3.928.079,08 | Q37: 100 | R37: 3.928.079,08 | S37: 3.554.822,70 | T37: 0,00
A38: Venta | B38: 467 | C38: Pago Realizado | D38: Jonatan Silvestri | E38: Cynthia | F38: JAVIER | H38: Pro Gas 6-1 | I38: 598486.37 | J38: 3867600 | K38: =ExportFacturacion[[#This Row],[Unitario]]*5% -> 193380 | L38: =ExportFacturacion[[#This Row],[Unitario]]-ExportFacturacion[[#This Row],[Descuento]] -> 3674220 | M38: 3.674.220,00 | N38: 385.793,10 | O38: 0,00 | P38: 4.060.013,10 | Q38: 50 | R38: 2.030.006,55 | S38: 1.837.110,00 | T38: 1.837.110,00
A39: Venta | B39: 471 | C39: Pago Realizado | D39: Santiago Barrerra | E39: Cynthia | F39: APYCE | H39: Box Kit x3 | J39: 101000 | L39: =ExportFacturacion[[#This Row],[Unitario]]-ExportFacturacion[[#This Row],[Descuento]] -> 101000 | M39: 1.229.600,00 | N39: 129.108,00 | O39: 0,00 | P39: 1.358.708,00 | Q39: 50 | R39: 679.354,00 | S39: 614.800,00 | T39: 614.800,00
H40: FN1 Pro | I40: 220132.92 | J40: 1188000 | K40: =ExportFacturacion[[#This Row],[Unitario]]*5% -> 59400 | L40: =ExportFacturacion[[#This Row],[Unitario]]-ExportFacturacion[[#This Row],[Descuento]] -> 1128600
A41: Venta | B41: 477 | C41: Pago Realizado | D41: Marcela Vazquez | E41: Cynthia | H41: Mesa | I41: 210000 | J41: 370000 | L41: =ExportFacturacion[[#This Row],[Unitario]]-ExportFacturacion[[#This Row],[Descuento]] -> 370000 | M41: 2.581.000,00 | N41: 271.005,00 | O41: 0,00 | P41: 2.852.005,00 | Q41: 100 | R41: 2.852.005,00 | S41: 2.581.000,00 | T41: 0,00
H42: FN2 Pro | I42: 398990.91 | J42: 2211000 | L42: =ExportFacturacion[[#This Row],[Unitario]]-ExportFacturacion[[#This Row],[Descuento]] -> 2211000
A43: Venta | B43: 484 | C43: Pago Realizado | D43: Adrian Ruben Basaez | E43: Stefania | G43: fedebasaez827@gmail.com | H43: Pro Gas 12-2 | I43: 1114422.9 | J43: 6446000 | L43: =ExportFacturacion[[#This Row],[Unitario]]-ExportFacturacion[[#This Row],[Descuento]] -> 6446000 | M43: 6.446.000,00 | N43: 676.830,00 | O43: 0,00 | P43: 7.122.830,00 | Q43: 50 | R43: 3.561.415,00 | S43: 3.223.000,00 | T43: 3.223.000,00
A44: Venta | B44: 487 | C44: Pago Realizado | D44: Piero Atilio Ferigutti | E44: Fernando | H44: FN1 Pro | I44: 220132.92 | J44: 1188000 | K44: =ExportFacturacion[[#This Row],[Unitario]]*0.452488% -> 5375.5574 | L44: =ExportFacturacion[[#This Row],[Unitario]]-ExportFacturacion[[#This Row],[Descuento]] -> 1182624.4 | M44: 1.182.624,44 | N44: 124.175,57 | O44: 0,00 | P44: 1.306.800,01 | Q44: 100 | R44: 1.312.740,00 | S44: 1.188.000,00 | T44: 0,00
A45: Venta | B45: 490 | C45: Pago Realizado | D45: Fabio Craviotto | E45: Fernando | H45: FN1 Pro | I45: 220132.92 | J45: 1188000 | K45: =ExportFacturacion[[#This Row],[Unitario]]*0.452488% -> 5375.5574 | L45: =ExportFacturacion[[#This Row],[Unitario]]-ExportFacturacion[[#This Row],[Descuento]] -> 1182624.4 | M45: 1.182.624,44 | N45: 124.175,57 | O45: 0,00 | P45: 1.306.800,01 | Q45: 100 | R45: 1.306.800,01 | S45: 1.182.624,44 | T45: 0,00
I47: =SUM(I2:I46) -> 19895234 | J47: =SUM(J2:J46) -> 112012903 | K47: =SUM(K2:K46) -> 4033636.4 | L47: =SUM(ExportFacturacion[Precio con descuento]) -> 1.0797927e+08 | N47: 1.0797927e+08

Sheet LISTA CONCEPTOS
A1: CUENTA | B1: SUBCUENTA
A2: Gasto de nómina | B2: ADQUISICION DE MERCANCIAS
A3: Gastos por servicios | B3: ALMACEN IFULL
A4: Gastos de venta | B4: ANTICIPO A PROVEEDORES
A5: Gastos financieros | B5: ASOCIACION NACIONAL DE TIENDAS DE AUTOSERVICIO Y DEPARTAMENTALES
A6: Gasto logistica | B6: CARGO NO IDENTIFICADO
A7: Reembolsos | B7: CASETAS
A8: Gastos de almacenaje | B8: COMISIONES BANCARIAS
A9: Viaticos Expo Pan WTC | B9: COMISIONES EUROFORNO
A10: Otros gastos operativos | B10: COMISIONES SOBRE VENTAS
A11: ANTICIPO A PROVEEDORES | B11: COMISIONES VENDEDORES
A12: CARGOS NO RECONOCIDOS BBVA | B12: CONSULTORIA ANA GPT
... A16: Gastos de Viaje y Transportacion | B16: EQUIPO DE PROTECCION PERSONAL
B17: EQUIPO PARA VENDEDORES (CARGADOR, USB,PILAS)
B18: ESTACIONAMIENTOS
B19: EXPO FOOD SERVICE DE MEXICO
B20: FERRETERIA Y HERRAMIENTAS PARA BODEGA TOLUCA
B21: GASOLINA FABIO
B22: GASTOS VARIOS
B23: GASTOS VARIOS (FABIO)
B24: HERRERIA BODEGA TOLUCA
B25: IMPUESTOS ANUALES
B26: IMPUESTOS FEDERALES
B27: IMPUESTOS ISR RET
B28: IMPUESTOS IVA RET
... B97: PUBLICIDAD DIGITAL MANTTO PAG. INTERNET-QUITO, ECUADOR
