Workbook

Sheet Nov'25
A1: Estado de Resultados 2025
A2: Concepto | B2: 45962 | C2: %
A3: Ventas Netas | B3: =ExportFacturacion[[#Totals],[Precio con Descuento]] -> 65841302 | C3: 1
A4: Descuentos Realizados | B4: =ExportFacturacion[[#Totals],[Descuento]] -> 3236891.9 | C4: =(B4*C3)/B3 -> 0.049162027
A5: Total Ingresos | B5: =B3-B4 -> 62604410 | C5: 1
A6: Costo total | B6: =ExportFacturacion[[#Totals],[Costo]] -> 9465758.9 | C6: 0.33
A7: Utilidad Marginal | B7: =B5-B6 -> 53138651 | C7: =(B7*C5)/B5 -> 0.84880045
A10: GASTOS VARIABLES | B10: =SUM(B11:B18) -> 26297220 | C10: =(B10*$C$5)/$B$5 -> 0.4200538
A11: COMISIONES BANCARIAS | B11: =+Gastos!C10 -> 49496 | C11: =(B11*$C$5)/$B$5 -> 0.00079061523
A12: COMISIONES DISTRIBUIDORES | B12: =+Gastos!C15 -> 838302.3 | C12: =(B12*$C$5)/$B$5 -> 0.013390467
A13: COMISIONES VENTAS | B13: =+Gastos!C13 -> 4288669.1 | C13: =(B13*$C$5)/$B$5 -> 0.068504265
A14: EXTRAORDINARIOS | B14: =+Gastos!C33 -> 19486331 | C14: =(B14*$C$5)/$B$5 -> 0.31126131
A15: FLETES | B15: =+Gastos!C35 -> 0 | C15: =(B15*$C$5)/$B$5 -> 0
A16: IMPUESTOS | B16: =+Gastos!C119 -> 1634422.5 | C16: =(B16*$C$5)/$B$5 -> 0.026107147
A17: MARKETING | B17: 0 | C17: =(B17*$C$5)/$B$5 -> 0
A18: PUESTA EN MARCHA | B18: 0 | C18: =(B18*$C$5)/$B$5 -> 0
A20: GASTOS FIJOS | B20: =SUM(B21:B22) -> 11386503 | C20: =(B20*$C$5)/$B$5 -> 0.18188021
A21: LOCAL | B21: =+Gastos!C130 -> 3898583.2 | C21: =(B21*$C$5)/$B$5 -> 0.0622733
A22: SUELDOS | B22: =+Gastos!C139 -> 7487920 | C22: =(B22*$C$5)/$B$5 -> 0.11960691
A24: GASTOS TOTALES | B24: =+B10+B20 -> 37683724
A26: UTILIDAD NETA | B26: =B7-B10-B20 -> 15454927 | C26: =(B26*C5)/B5 -> 0.24686643
A29: INVERSIONES
A30: INVERSIONES

Sheet Gastos
A1: Fecha | B1: Descripción | C1: Importe | D1: Categoría | E1: SubCategoría
A2: 45971 | B2: Comision Gestion Tranaferancia de Fondos | C2: 1000 | D2: Comisiones Bancarias | E2: Comisiones Bancarias
A3: 45972 | B3: Debito Com. Varias | Transf. al Ext. | C3: 14832 | D3: Impuestos | E3: Comisiones Bancarias
A4: 45972 | B4: Debito Com. Varias | Transf. al Ext. | C4: 29664 | D4: Impuestos | E4: Comisiones Bancarias
A5: 45974 | B5: Comision Gestion de Fondos | C5: 1000 | D5: Comisiones Bancarias | E5: Comisiones Bancarias
A6: 45974 | B6: Comision Gestion de Fondos | C6: 1000 | D6: Comisiones Bancarias | E6: Comisiones Bancarias
A7: 45975 | B7: Comision Gestion de Fondos | C7: 1000 | D7: Comisiones Bancarias | E7: Comisiones Bancarias
A8: 45986 | B8: Comision Gestion de Fondos | C8: 1000 | D8: Comisiones Bancarias | E8: Comisiones Bancarias
A9: 45986 | B9: Comision Gestion de Fondos | C9: 1000 | D9: Comisiones Bancarias | E9: Comisiones Bancarias
B10: Comisiones Bancarias | C10: =SUM(C3:C9) -> 49496
B11: Comisiones Cynthia | Oct´25 | C11: 1697335.3 | D11: Comisiones Ventas | E11: Comisiones Ventas
B12: Comisiones Lelia | Oct´25 | C12: 2591333.8 | D12: Comisiones Ventas | E12: Comisiones Ventas
B13: Comisiones de Ventas | C13: =SUM(C11:C12) -> 4288669.1
A14: 45974 | B14: Comisiones Javier Oct´25 | C14: 838302.3 | D14: Comisiones Ventas | E14: Comisiones Ventas
B15: Comisiones Distribuidores | C15: =SUM(C14) -> 838302.3
A16: 45964 | B16: Pago | Desarrollo de Soluciones Digitales | Fact 00002-00000012 | C16: 4116696.6 | D16: Otros Servicios | E16: App Sumar | F16: Desarrollo Custom Pack 2
A17: 45966 | B17: Transf | Cuentas Propias | C17: 100000 | D17: Otros Servicios | E17: Gastos Administrativos | F17: Movimiento Cuenta 0002410-3 363-5
A18: 45968 | B18: Pago | Francisco Ricardo Jose | Fact 00002-00001091 | C18: 526133.4 | D18: Activos | E18: Accesorios | F18: Regulador EQA de GAS 6.4mm 0.03bar (3 piezas)
A19: 45968 | B19: Pago | Desarrollo de Soluciones Digitales | Fact 00002-00000019 | C19: 512540.8 | D19: Otros Servicios | E19: App Sumar | F19: Servicio APP Noviembre 2025
A20: 45968 | B20: Pago | Alba Posse Patricia Maria | Fact 00001-00000020 | C20: 1262000 | D20: Otros Servicios | E20: Selección de Personal | F20: Servicio de Selección de Personal
A21: 45971 | B21: Pago | Apyce | Fact 00010-00000028 | C21: 200000 | D21: Otros Servicios | E21: Gastos Administrativos | F21: Pago de 1 Entrada a Cena Apyce Aniversario
A22: 45971 | B22: Pago | Mol & Band | Fact 00003-00003384 | C22: 257193.4 | D22: Activos | E22: Accesorios | F22: Base con ruedas para Horno
A23: 45972 | B23: Pago | Bustos Alexis Emiliano | Fact 00002-00000772 | C23: 47800 | D23: Marketing | E23: Publicidad | F23: Impresión de vinilo en PVC con soporte
A24: 45973 | B24: Pago | Cia de Seguros La Mercantil Andina | C24: 17075.92 | D24: Otros Servicios | E24: Gastos Administrativos | F24: Poliza de Accidentes Personales
A25: 45974 | B25: Pago | Nicolas Manuel Torres | Fact 00002-00000103 | C25: 67760 | D25: Otros Servicios | E25: Gastos Administrativos | F25: Bidones de agua (8 piezas) Sep - Oct 2025
A26: 45974 | B26: Pago | Nicolas Manuel Torres | Fact 00002-00000114 | C26: 67760 | D26: Otros Servicios | E26: Gastos Administrativos | F26: Bidones de agua (8 piezas) Oct - Nov 2025
A27: 45975 | B27: Pago | Battaglia Daniel Damian | Fact 00002-00001013 | C27: 762743.4 | D27: Marketing | E27: Publicidad | F27: Transporte a Cena Apyce
... A32: 45988 | B32: Pago | Leonardo Agustin Pascual | Fact 00002-00000078 | C32: 2200000 | D32: Marketing | E32: Publicidad | F32: Avisos publicitarios y film maker en RRSS y MIMA
B33: Extraordinarios | C33: =SUM(C16:C32) -> 19486331
A34: 45954 | B34: Pago | Autoelevadores y Gruas | Oct 2025 | Fact 7537 | D34: Fletes | E34: Fletes
B35: Fletes | C35: =C34 -> 0
A36: 45964 | B36: Impuesto Deb. Ley 25.413 | C36: 45803.92 | D36: Impuestos | E36: Ley 25.413
A37: 45965 | B37: Imp. Ing. Brutos Sircreb | C37: 67.63 | D37: Impuestos | E37: Sircreb
A38: 45965 | B38: Impuesto Deb. Ley 25.413 | C38: 1083.55 | D38: Impuestos | E38: Ley 25.413
A39: 45965 | B39: Impuesto Cre. Ley 25.413 | C39: 4057.56 | D39: Impuestos | E39: Ley 25.413
A40: 45965 | B40: Impuesto Deb. Ley 25.413 | C40: 0.41 | D40: Impuestos | E40: Ley 25.413
A41: 45966 | B41: Imp. Ing. Brutos Sircreb | C41: 169.47 | D41: Impuestos | E41: Sircreb
A42: 45966 | B42: Impuesto Cre. Ley 25.413 | C42: 10168.41 | D42: Impuestos | E42: Ley 25.413
A43: 45966 | B43: Impuesto Deb. Ley 25.413 | C43: 1.02 | D43: Impuestos | E43: Ley 25.413
A44: 45968 | B44: Imp. Ing. Brutos Sircreb | C44: 64.93 | D44: Impuestos | E44: Sircreb
A45: 45968 | B45: Imp. Ing. Brutos Sircreb | C45: 373.43 | D45: Impuestos | E45: Sircreb
A46: 45968 | B46: Impuesto Deb. Ley 25.413 | C46: 31250.8 | D46: Impuestos | E46: Ley 25.413
A47: 45968 | B47: Impuesto Cre. Ley 25.413 | C47: 26301.54 | D47: Impuestos | E47: Ley 25.413
... A118: 45989 | B118: Impuesto Deb. Ley 25.413 | C118: 3.92 | D118: Impuestos | E118: Ley 25.413
B119: Impuestos | C119: =SUM(C36:C118) -> 1634422.5
A120: 45964 | B120: Pago | Prosegur Noviembre 2025 Deb Autom. | C120: 98403.77 | D120: Local | E120: Seguridad
A121: 45965 | B121: Pago | Personal Flow | Deb Autom | C121: 28135.65 | D121: Local | E121: Internet
A122: 45965 | B122: Pago | Personal Flow | Deb Autom | C122: 152455.29 | D122: Local | E122: Internet
A123: 45968 | B123: Pago | Veronica Valeria Rigante | Fact 00002-00000970 | C123: 303000 | D123: Local | E123: Honorarios Contables
A124: 45968 | B124: Pago | Viviana Fuertes | Alquiler | Fact 00002-00000265 | C124: 304792 | D124: Local | E124: Alquiler
A125: 45968 | B125: Pago | Reynoso Agustina | Fact 00001-00000006 | C125: 2300000 | D125: Marketing | E125: Creacion de Contenido
A126: 45972 | B126: Pago | Soluciones Online | Nov 2025 | Deb. Autom. | Fact 000002-00481188 | C126: 154033 | D126: Local | E126: Internet
A127: 45973 | B127: Pago | Pay Per Tic | Deb Autom | C127: 20717.48 | D127: Local | E127: Internet
A128: 45974 | B128: Pago | Autoelevadores y Gruas | Nov 2025 | Fact 7537 | C128: 108443.4 | D128: Local | E128: Alquiler
A129: 45988 | B129: Pago | Edenor | Energia Electrica | C129: 428602.61 | D129: Local | E129: Edenor
B130: Local | C130: =SUM(C120:C129) -> 3898583.2
A131: 45964 | B131: Pago | Sueldo Lelia Bertoni | Oct'25 | C131: 443532 | D131: Sueldos | E131: Sueldos
A132: 45964 | B132: Pago | Sueldo Cynthia Fernández | Oct'25 | C132: 583620 | D132: Sueldos | E132: Sueldos
A133: 45964 | B133: Pago | Sueldo Diego Argiró | Oct'25 | C133: 2391734 | D133: Sueldos | E133: Sueldos
A134: 45965 | B134: Sueldo Cynthia | Oct´25 | C134: 250000 | D134: Sueldos | E134: Sueldos
A135: 45965 | B135: Sueldo Lelia| Oct´25 | C135: 200000 | D135: Sueldos | E135: Sueldos
A136: 45965 | B136: Sueldo Diego| Oct´25 | C136: 3388266 | D136: Sueldos | E136: Sueldos
A137: 45965 | B137: Sueldo Stefania Oct´25 | C137: 50000 | D137: Sueldos | E137: Sueldos
A138: 45974 | B138: Sueldo Liquidacion Axel Fernando Oct´25 | C138: 180768 | D138: Sueldos | E138: Sueldos
B139: Sueldos | C139: =SUM(C131:C138) -> 7487920

Sheet Ventas Nov 2025
A1: Tipo de Operacion | B1: ID Operacion | C1: Status | D1: Cliente | E1: Vendedor | F1: Referido | G1: Correo | H1: Equipo | I1: Costo | J1: Unitario | K1: Descuento | L1: Precio con Descuento | M1: Columna1
A2: Venta | B2: 180 | D2: Janet Arcos | H2: Horno FN1 Pro | I2: 220132.92 | J2: 6446000 | K2: =ExportFacturacion[[#This Row],[Precio con Descuento]]-ExportFacturacion[[#This Row],[Unitario]] -> 0 | L2: 6446000
A3: Venta | B3: 424 | C3: Pago Realizado | D3: Diego Armando Coronel | E3: Lelia | H3: Horno FN2 Pro | I3: 398990.91 | J3: 2211000 | K3: 97426.61 | L3: 2113573.4
A4: Venta | B4: 447 | C4: Pago Realizado | D4: Nicolas La Mala | E4: Lelia | H4: Horno Pro Gas 24-3 | J4: 10820000 | K4: =ExportFacturacion[[#This Row],[Precio con Descuento]]-ExportFacturacion[[#This Row],[Unitario]] -> 0 | L4: 10820000
A5: Venta | B5: 467 | D5: Jonathan Silvestri | H5: Horno Pro Gas 6-1 | I5: 598486.37 | J5: 3867600 | K5: 193380 | L5: 3674220
A6: Venta | B6: 493 | C6: Pago Realizado | D6: Gaston Martinez | E6: Cynthia | G6: gastonfermartinez@gmail.com | H6: Horno FN1 Pro | I6: 220132.92 | J6: 1188000 | K6: =ExportFacturacion[[#This Row],[Precio con Descuento]]-ExportFacturacion[[#This Row],[Unitario]] -> 0 | L6: 1188000
A7: Venta | B7: 495 | C7: Pago Realizado | D7: Oscar Waldemar Flaumer | E7: Lelia | G7: juanberticje9@gmail.com | H7: Techo Pro Gas 6 y 12 | J7: 612000 | K7: =ExportFacturacion[[#This Row],[Precio con Descuento]]-ExportFacturacion[[#This Row],[Unitario]] -> 0 | L7: 612000
A8: Venta | B8: 506 | C8: Pago Realizado | D8: Emanuel Facundo Salva | E8: Cynthia | G8: salvaemanuelfacundo@gmail.com | H8: Horno Pro Gas 6-1 | I8: 598486.37 | J8: 3867600 | K8: 187790.54 | L8: 3679809.5
H9: Regulador | J9: 106000
H10: Manguito | J10: 12000
A11: Venta | B11: 510 | C11: Pago Realizado | D11: Facundo Reyero | E11: Lelia | H11: Horno Pro Gas 6-1 | I11: 598486.37 | J11: 3867600 | K11: 800206.44 | L11: 3067393.6
H12: Pala rectangular 35 | I12: 28147.47 | J12: 91000 | K12: =ExportFacturacion[[#This Row],[Precio con Descuento]]-ExportFacturacion[[#This Row],[Unitario]] -> 0 | L12: 91000
H13: Cepillo para piedra | I13: 29803.21 | J13: 120100 | K13: =ExportFacturacion[[#This Row],[Precio con Descuento]]-ExportFacturacion[[#This Row],[Unitario]] -> 0 | L13: 120100
H14: Box Kit 3 | J14: 101000 | K14: =ExportFacturacion[[#This Row],[Precio con Descuento]]-ExportFacturacion[[#This Row],[Unitario]] -> 0 | L14: 101000
A15: Venta | B15: 511 | C15: Pago Realizado | D15: Matias Martino | E15: Cynthia | H15: Horno FN1 Pro | I15: 220132.92 | J15: 1188000 | K15: =ExportFacturacion[[#This Row],[Precio con Descuento]]-ExportFacturacion[[#This Row],[Unitario]] -> 0 | L15: 1188000
A16: Venta | B16: 516 | C16: Pago Realizado | D16: Lucas Gastón Ayala | E16: Lelia | H16: Horno FN1 Pro | I16: 220132.92 | J16: 1188000 | K16: 118800 | L16: 1069200
A17: Venta | B17: 518 | D17: Nicolas Martin | H17: Horno Pro Gas 6-1 | I17: 598486.37 | J17: 3067393.6 | K17: 0 | L17: 3067393.6
A18: Venta | B18: 536 | C18: Pago Realizado | D18: Roald Alejandro Gonzalez Lascano | E18: Stefania | G18: emprenoa@gmail.com | H18: Horno FN2 Pro | I18: 398990.91 | J18: 2211000 | K18: 134073.96 | L18: 2076926
A19: Venta | B19: 542 | C19: Pago Realizado | D19: Matias Ariel Perez | E19: Lelia | G19: matiasarperez@gmail.com | H19: Horno Pro Gas 6-1 | I19: 598486.37 | J19: 3867600 | K19: 800206.44 | L19: 3067393.6
A20: Venta | B20: 559 | C20: Pago Realizado | D20: Esteban Laporte | E20: Stefania | G20: Esteban_laporte@hotmail.com | H20: Perchero para palas | I20: 92023 | J20: 287000 | K20: 20574.89 | L20: 266425.11
A21: Venta | B21: 576 | D21: Lucas Villalva | H21: Horno FN1 Pro | I21: 220132.92 | J21: 1188000 | K21: =ExportFacturacion[[#This Row],[Precio con Descuento]]-ExportFacturacion[[#This Row],[Unitario]] -> 0 | L21: 1188000
A22: Venta | B22: 579 | D22: Quimey Verturelli | H22: Horno FN2 Pro | I22: 398990.91 | J22: 2211000 | K22: =ExportFacturacion[[#This Row],[Precio con Descuento]]-ExportFacturacion[[#This Row],[Unitario]] -> 0 | L22: 2211000
A23: Venta | B23: 581 | D23: Cecilia Fuse | H23: Amasadora AM15 | I23: 599897.5 | J23: 1844330 | K23: 184433 | L23: 1659867
A24: Venta | B24: 589 | D24: Juan Carlos Caccaviello | H24: Horno Pro Gas 12-2 | I24: 1114422.9 | J24: 7000000 | K24: 700000 | L24: 6300000
A25: Venta | B25: 580 | D25: Alexis Nahuel Aguirre | H25: Horno Pro Gas 6-1 | I25: 598486.37 | J25: 3067000 | K25: =ExportFacturacion[[#This Row],[Precio con Descuento]]-ExportFacturacion[[#This Row],[Unitario]] -> 0 | L25: 3067000
A26: Venta | B26: 582 | D26: Matias Figueroa | H26: Horno Pro Gas 6-1 | I26: 598486.37 | J26: 3067000 | K26: =ExportFacturacion[[#This Row],[Precio con Descuento]]-ExportFacturacion[[#This Row],[Unitario]] -> 0 | L26: 3067000
A27: Venta | B27: 585 | D27: Nestor Romero Deza | H27: Horno Pro gas 12-2 | I27: 1114422.9 | J27: 5700000 | K27: =ExportFacturacion[[#This Row],[Precio con Descuento]]-ExportFacturacion[[#This Row],[Unitario]] -> 0 | L27: 5700000
I28: =SUM(I2:I27) -> 9465758.9 | J28: =SUM(J2:J27) -> 69196224 | K28: =SUM(K2:K27) -> 3236891.9 | L28: =SUM(L2:L27) -> 65841302

Sheet LISTA CONCEPTOS
A1: CUENTA | B1: SUBCUENTA
A2: Gasto de nómina | B2: ADQUISICION DE MERCANCIAS
A3: Gastos por servicios | B3: ALMACEN IFULL
A4: Gastos de venta | B4: ANTICIPO A PROVEEDORES
A5: Gastos financieros | B5: ASOCIACION NACIONAL DE TIENDAS DE AUTOSERVICIO Y DEPARTAMENTALES
A6: Gasto logistica | B6: CARGO NO IDENTIFICADO
A7: Reembolsos | B7: CASETAS
A8: Gastos de almacenaje | B8: COMISIONES BANCARIAS
A9: Viaticos Expo Pan WTC | B9: COMISIONES EUROFORNO
A10: Otros gastos operativos | B10: COMISIONES SOBRE VENTAS
A11: ANTICIPO A PROVEEDORES | B11: COMISIONES VENDEDORES
A12: CARGOS NO RECONOCIDOS BBVA | B12: CONSULTORIA ANA GPT
... A16: Gastos de Viaje y Transportacion | B16: EQUIPO DE PROTECCION PERSONAL
B17: EQUIPO PARA VENDEDORES (CARGADOR, USB,PILAS)
B18: ESTACIONAMIENTOS
B19: EXPO FOOD SERVICE DE MEXICO
B20: FERRETERIA Y HERRAMIENTAS PARA BODEGA TOLUCA
B21: GASOLINA FABIO
B22: GASTOS VARIOS
B23: GASTOS VARIOS (FABIO)
B24: HERRERIA BODEGA TOLUCA
B25: IMPUESTOS ANUALES
B26: IMPUESTOS FEDERALES
B27: IMPUESTOS ISR RET
B28: IMPUESTOS IVA RET
... B97: PUBLICIDAD DIGITAL MANTTO PAG. INTERNET-QUITO, ECUADOR
